what2-0.4.2.dist-info/METADATA
what2-0.4.2.dist-info/WHEEL
what2-0.4.2.dist-info/entry_points.txt
what2/debug/__init__.py
what2/debug/debug.py
what2/debug/notebook.py
what2/debug/py.typed
what2/py.typed
what2/util.py
what2-0.4.2.dist-info/RECORD
