Metadata-Version: 2.1
Name: what2
Version: 0.4.2
Summary: A collection of my random dev tools and scripts.
Author-Email: Marc Edwards <marc@mlwhat.com>
License: MIT
Classifier: Development Status :: 3 - Alpha
Project-URL: Repository, https://github.com/alwaysmpe/what2
Requires-Python: >=3.12
